{
	"info": {
		"_postman_id": "0b4c6eb9-592b-4b11-a960-557fbdb825e0",
		"name": "Fixify API Collection",
		"description": "Complete API collection for Fixify backend",
		"schema": "https://schema.getpostman.com/json/collection/v2.1.0/collection.json",
		"_exporter_id": "24594422"
	},
	"item": [
		{
			"name": "Auth",
			"item": [
				{
					"name": "Register User",
					"request": {
						"method": "POST",
						"header": [
							{
								"key": "Content-Type",
								"value": "application/json"
							}
						],
						"body": {
							"mode": "raw",
							"raw": "{\n  \"firstName\": \"Arbaz\",\n  \"lastName\": \"Shaikh\",\n  \"email\": \"arbazshaikh@gmail.com\",\n  \"phone\": \"6351973814\",\n  \"password\": \"123\",\n  \"role\": \"customer\",\n  \"addresses\": [\n    {\n      \"label\": \"Home\",\n      \"line1\": \"221 Baker Street\",\n      \"city\": \"London\",\n      \"postalCode\": \"400001\",\n      \"lat\": 19.07,\n      \"lng\": 72.87\n    }\n  ],\n  \"gender\" :\"male\"\n}"
						},
						"url": {
							"raw": "{{base_url}}/auth/register",
							"host": [
								"{{base_url}}"
							],
							"path": [
								"auth",
								"register"
							]
						}
					},
					"response": []
				},
				{
					"name": "Login User",
					"request": {
						"method": "POST",
						"header": [
							{
								"key": "Content-Type",
								"value": "application/json"
							}
						],
						"body": {
							"mode": "raw",
							"raw": "{\n  \"emailOrPhone\": \"arbazshaikh@gmail.com\",\n  \"password\": \"123\"\n}"
						},
						"url": {
							"raw": "{{base_url}}/auth/login",
							"host": [
								"{{base_url}}"
							],
							"path": [
								"auth",
								"login"
							]
						}
					},
					"response": []
				},
				{
					"name": "Get Profile (Token Required)",
					"request": {
						"method": "GET",
						"header": [
							{
								"key": "Authorization",
								"value": "Bearer {{token}}"
							}
						],
						"url": {
							"raw": "{{base_url}}/auth/profile",
							"host": [
								"{{base_url}}"
							],
							"path": [
								"auth",
								"profile"
							]
						}
					},
					"response": []
				},
				{
					"name": "Forgot Password - Send OTP",
					"request": {
						"method": "POST",
						"header": [
							{
								"key": "Content-Type",
								"value": "application/json"
							}
						],
						"body": {
							"mode": "raw",
							"raw": "{\n  \"email\": \"moh.riyazpathan@gmail.com\"\n}"
						},
						"url": {
							"raw": "{{base_url}}/auth/forgot-password",
							"host": [
								"{{base_url}}"
							],
							"path": [
								"auth",
								"forgot-password"
							]
						}
					},
					"response": []
				},
				{
					"name": "Verify OTP",
					"request": {
						"method": "POST",
						"header": [
							{
								"key": "Content-Type",
								"value": "application/json"
							}
						],
						"body": {
							"mode": "raw",
							"raw": "{\n  \"email\": \"moh.riyazpathan@gmail.com\",\n  \"otp\": \"163857\"\n}"
						},
						"url": {
							"raw": "{{base_url}}/auth/verify-otp",
							"host": [
								"{{base_url}}"
							],
							"path": [
								"auth",
								"verify-otp"
							]
						}
					},
					"response": []
				},
				{
					"name": "Reset Password",
					"request": {
						"method": "POST",
						"header": [
							{
								"key": "Content-Type",
								"value": "application/json"
							}
						],
						"body": {
							"mode": "raw",
							"raw": "{\n  \"email\": \"moh.riyazpathan@gmail.com\",\n  \"otp\": \"163857\",\n  \"newPassword\": \"1234\"\n}"
						},
						"url": {
							"raw": "{{base_url}}/auth/reset-password",
							"host": [
								"{{base_url}}"
							],
							"path": [
								"auth",
								"reset-password"
							]
						}
					},
					"response": []
				}
			]
		},
		{
			"name": "Users",
			"item": [
				{
					"name": "Get My Profile",
					"request": {
						"method": "GET",
						"header": [
							{
								"key": "Authorization",
								"value": "Bearer {{token}}"
							}
						],
						"url": {
							"raw": "{{base_url}}/users/me",
							"host": [
								"{{base_url}}"
							],
							"path": [
								"users",
								"me"
							]
						}
					},
					"response": []
				},
				{
					"name": "Update My Profile",
					"request": {
						"method": "PUT",
						"header": [
							{
								"key": "Content-Type",
								"value": "application/json"
							},
							{
								"key": "Authorization",
								"value": "Bearer {{token}}"
							}
						],
						"body": {
							"mode": "raw",
							"raw": "{\n  \"firstName\": \"RiyazKhan\",\n  \"lastName\": \"Pathan\",\n  \"email\":\"moh.riyazpathan@gmail.com\",\n  \"phone\":\"9909221451\",\n  \"role\":\"admin\"\n}"
						},
						"url": {
							"raw": "{{base_url}}/users/me",
							"host": [
								"{{base_url}}"
							],
							"path": [
								"users",
								"me"
							]
						}
					},
					"response": []
				},
				{
					"name": "Get All Users (Admin)",
					"request": {
						"method": "GET",
						"header": [
							{
								"key": "Authorization",
								"value": "Bearer {{token}}"
							}
						],
						"url": {
							"raw": "{{base_url}}/users/all",
							"host": [
								"{{base_url}}"
							],
							"path": [
								"users",
								"all"
							]
						}
					},
					"response": []
				},
				{
					"name": "Get User by ID",
					"request": {
						"method": "GET",
						"header": [
							{
								"key": "Authorization",
								"value": "Bearer {{token}}"
							}
						],
						"url": {
							"raw": "{{base_url}}/users/{{userId}}",
							"host": [
								"{{base_url}}"
							],
							"path": [
								"users",
								"{{userId}}"
							]
						}
					},
					"response": []
				},
				{
					"name": "Delete User (Admin)",
					"request": {
						"method": "DELETE",
						"header": [
							{
								"key": "Authorization",
								"value": "Bearer {{token}}"
							}
						],
						"url": {
							"raw": "{{base_url}}/users/{{userId}}",
							"host": [
								"{{base_url}}"
							],
							"path": [
								"users",
								"{{userId}}"
							]
						}
					},
					"response": []
				}
			]
		},
		{
			"name": "Services",
			"item": [
				{
					"name": "Get All Services",
					"request": {
						"method": "GET",
						"header": [],
						"url": {
							"raw": "{{base_url}}/services/services",
							"host": [
								"{{base_url}}"
							],
							"path": [
								"services",
								"services"
							]
						}
					},
					"response": []
				},
				{
					"name": "Create Service",
					"request": {
						"method": "POST",
						"header": [
							{
								"key": "Content-Type",
								"value": "application/json"
							}
						],
						"body": {
							"mode": "raw",
							"raw": "{\n  \"name\": \"AC Repair\",\n  \"description\": \"Fix AC cooling issues\",\n  \"category\": \"Home Appliance\",\n  \"basePrice\": 500,\n  \"iconUrl\": \"https://example.com/ac.png\"\n}"
						},
						"url": {
							"raw": "{{base_url}}/services/service",
							"host": [
								"{{base_url}}"
							],
							"path": [
								"services",
								"service"
							]
						}
					},
					"response": []
				},
				{
					"name": "Update Service",
					"request": {
						"method": "PUT",
						"header": [
							{
								"key": "Content-Type",
								"value": "application/json"
							}
						],
						"body": {
							"mode": "raw",
							"raw": "{\n  \"description\": \"Updated description\"\n}"
						},
						"url": {
							"raw": "{{base_url}}/services/service/{{serviceId}}",
							"host": [
								"{{base_url}}"
							],
							"path": [
								"services",
								"service",
								"{{serviceId}}"
							]
						}
					},
					"response": []
				},
				{
					"name": "Delete Service",
					"request": {
						"method": "DELETE",
						"header": [],
						"url": {
							"raw": "{{base_url}}/services/service/{{serviceId}}",
							"host": [
								"{{base_url}}"
							],
							"path": [
								"services",
								"service",
								"{{serviceId}}"
							]
						}
					},
					"response": []
				}
			]
		},
		{
			"name": "Logs",
			"item": [
				{
					"name": "BackEnd Logs FileNames",
					"request": {
						"method": "GET",
						"header": [],
						"url": {
							"raw": "{{base_url}}/logs/backend-logs",
							"host": [
								"{{base_url}}"
							],
							"path": [
								"logs",
								"backend-logs"
							]
						}
					},
					"response": []
				},
				{
					"name": "BackEnd Logs FileContent",
					"request": {
						"method": "GET",
						"header": [],
						"url": {
							"raw": "{{base_url}}/logs/backend-logs/2025-12-01.log",
							"host": [
								"{{base_url}}"
							],
							"path": [
								"logs",
								"backend-logs",
								"2025-12-01.log"
							]
						}
					},
					"response": []
				},
				{
					"name": "BackEnd Logs Last FileContent",
					"request": {
						"method": "GET",
						"header": [],
						"url": {
							"raw": "{{base_url}}/logs/backend-logs/2025-12-01.log/last/10",
							"host": [
								"{{base_url}}"
							],
							"path": [
								"logs",
								"backend-logs",
								"2025-12-01.log",
								"last",
								"10"
							]
						}
					},
					"response": []
				},
				{
					"name": "BackEnd Logs File Download",
					"request": {
						"method": "GET",
						"header": [],
						"url": {
							"raw": "{{base_url}}/logs/backend-logs/2025-12-01.log/download",
							"host": [
								"{{base_url}}"
							],
							"path": [
								"logs",
								"backend-logs",
								"2025-12-01.log",
								"download"
							]
						}
					},
					"response": []
				}
			]
		},
		{
			"name": "Booking (Without Auth)",
			"item": [
				{
					"name": "Create Booking",
					"request": {
						"method": "POST",
						"header": [
							{
								"key": "Content-Type",
								"value": "application/json"
							}
						],
						"body": {
							"mode": "raw",
							"raw": "{\n  \"customer_id\": \"692fff09b0f6bc46c16bba74\",\n  \"service_id\": \"692f3d791166b1727bd9d46b\",\n  \"address\": {\n    \"line1\": \"Sanjar Park 2\",\n    \"city\": \"Ahmedabad\",\n    \"postalCode\": \"380028\"\n  },\n  \"issue_images\": [\n    \"img1.jpg\",\n    \"img2.jpg\"\n  ]\n}"
						},
						"url": {
							"raw": "{{base_url}}/bookings",
							"host": [
								"{{base_url}}"
							],
							"path": [
								"bookings"
							]
						}
					},
					"response": []
				},
				{
					"name": "Get All Bookings",
					"request": {
						"method": "GET",
						"header": [],
						"url": {
							"raw": "{{base_url}}/bookings",
							"host": [
								"{{base_url}}"
							],
							"path": [
								"bookings"
							]
						}
					},
					"response": []
				},
				{
					"name": "Get Booking by ID",
					"request": {
						"method": "GET",
						"header": [],
						"url": {
							"raw": "{{base_url}}/bookings/:id",
							"host": [
								"{{base_url}}"
							],
							"path": [
								"bookings",
								":id"
							],
							"variable": [
								{
									"key": "id",
									"value": "6931d0b2995aebc271a9340c"
								}
							]
						}
					},
					"response": []
				},
				{
					"name": "Update Booking",
					"request": {
						"method": "PUT",
						"header": [
							{
								"key": "Content-Type",
								"value": "application/json"
							}
						],
						"body": {
							"mode": "raw",
							"raw": "{\n  \"address\": {\n    \"line1\": \"Updated Address\",\n    \"city\": \"Ahmedabad\",\n    \"postalCode\": \"380050\"\n  },\n  \"issue_images\": [\n    \"new1.jpg\",\n    \"new2.jpg\"\n  ]\n}"
						},
						"url": {
							"raw": "{{base_url}}/bookings/:id",
							"host": [
								"{{base_url}}"
							],
							"path": [
								"bookings",
								":id"
							],
							"variable": [
								{
									"key": "id",
									"value": "6931d0b2995aebc271a9340c"
								}
							]
						}
					},
					"response": []
				},
				{
					"name": "Delete Booking",
					"request": {
						"method": "DELETE",
						"header": [],
						"url": {
							"raw": "{{base_url}}/bookings/:id",
							"host": [
								"{{base_url}}"
							],
							"path": [
								"bookings",
								":id"
							],
							"variable": [
								{
									"key": "id",
									"value": "6931d0b2995aebc271a9340c"
								}
							]
						}
					},
					"response": []
				},
				{
					"name": "Cancel Booking",
					"request": {
						"method": "PUT",
						"header": [],
						"url": {
							"raw": "{{base_url}}/bookings/:id/cancel",
							"host": [
								"{{base_url}}"
							],
							"path": [
								"bookings",
								":id",
								"cancel"
							],
							"variable": [
								{
									"key": "id",
									"value": "6931d0e9995aebc271a93411"
								}
							]
						}
					},
					"response": []
				},
				{
					"name": "Assign Contractor",
					"request": {
						"method": "PUT",
						"header": [
							{
								"key": "Content-Type",
								"value": "application/json"
							}
						],
						"body": {
							"mode": "raw",
							"raw": "{\n  \"contractor_id\": \"69300ab739d6b0e7c2beeeca\"\n}"
						},
						"url": {
							"raw": "{{base_url}}/bookings/:id/assign",
							"host": [
								"{{base_url}}"
							],
							"path": [
								"bookings",
								":id",
								"assign"
							],
							"variable": [
								{
									"key": "id",
									"value": "6931d0e9995aebc271a93411"
								}
							]
						}
					},
					"response": []
				},
				{
					"name": "Reject Booking",
					"request": {
						"method": "PUT",
						"header": [
							{
								"key": "Content-Type",
								"value": "application/json"
							}
						],
						"body": {
							"mode": "raw",
							"raw": "{\n  \"user_id\": \"6931a93ef651b481edd5da86\"\n}"
						},
						"url": {
							"raw": "{{base_url}}/bookings/:id/reject",
							"host": [
								"{{base_url}}"
							],
							"path": [
								"bookings",
								":id",
								"reject"
							],
							"variable": [
								{
									"key": "id",
									"value": "6931d0e9995aebc271a93411"
								}
							]
						}
					},
					"response": []
				}
			]
		}
	],
	"event": [
		{
			"listen": "prerequest",
			"script": {
				"type": "text/javascript",
				"packages": {},
				"requests": {},
				"exec": [
					""
				]
			}
		},
		{
			"listen": "test",
			"script": {
				"type": "text/javascript",
				"packages": {},
				"requests": {},
				"exec": [
					""
				]
			}
		}
	],
	"variable": [
		{
			"key": "base_url",
			"value": "http://localhost:3000"
		},
		{
			"key": "token",
			"value": ""
		},
		{
			"key": "userId",
			"value": ""
		},
		{
			"key": "serviceId",
			"value": ""
		},
		{
			"key": "base_url",
			"value": "",
			"disabled": true
		},
		{
			"key": "bookingId",
			"value": ""
		},
		{
			"key": "customerId",
			"value": ""
		},
		{
			"key": "contractorId",
			"value": ""
		}
	]
}